beplibrarylib/__init__.py
beplibrarylib/myfunctions.py
bep_framework-1.1.1.dist-info/METADATA
bep_framework-1.1.1.dist-info/WHEEL
bep_framework-1.1.1.dist-info/top_level.txt
bep_framework-1.1.1.dist-info/RECORD
